tno.mpc.mpyc.secure_learning-1.1.1-py3.8-nspkg.pth
tno/mpc/mpyc/secure_learning/__init__.py
tno/mpc/mpyc/secure_learning/exceptions.py
tno/mpc/mpyc/secure_learning/metrics.py
tno/mpc/mpyc/secure_learning/py.typed
tno/mpc/mpyc/secure_learning/regularizers.py
tno/mpc/mpyc/secure_learning/models/__init__.py
tno/mpc/mpyc/secure_learning/models/common_gradient_forms.py
tno/mpc/mpyc/secure_learning/models/grid_cv.py
tno/mpc/mpyc/secure_learning/models/secure_elastic_nets.py
tno/mpc/mpyc/secure_learning/models/secure_lasso.py
tno/mpc/mpyc/secure_learning/models/secure_linear.py
tno/mpc/mpyc/secure_learning/models/secure_logistic.py
tno/mpc/mpyc/secure_learning/models/secure_model.py
tno/mpc/mpyc/secure_learning/models/secure_ridge.py
tno/mpc/mpyc/secure_learning/models/secure_svm.py
tno/mpc/mpyc/secure_learning/solvers/__init__.py
tno/mpc/mpyc/secure_learning/solvers/gd_solver.py
tno/mpc/mpyc/secure_learning/solvers/solver.py
tno/mpc/mpyc/secure_learning/test/__init__.py
tno/mpc/mpyc/secure_learning/test/mpyc_test_utils.py
tno/mpc/mpyc/secure_learning/test/test_gradients.py
tno/mpc/mpyc/secure_learning/test/test_metrics.py
tno/mpc/mpyc/secure_learning/test/test_regularizers.py
tno/mpc/mpyc/secure_learning/test/plaintext_utils/__init__.py
tno/mpc/mpyc/secure_learning/test/plaintext_utils/plaintext_gradients.py
tno/mpc/mpyc/secure_learning/test/plaintext_utils/plaintext_metrics.py
tno/mpc/mpyc/secure_learning/test/plaintext_utils/plaintext_objective_functions.py
tno/mpc/mpyc/secure_learning/utils/__init__.py
tno/mpc/mpyc/secure_learning/utils/data_permutator.py
tno/mpc/mpyc/secure_learning/utils/matrix_augmenter.py
tno/mpc/mpyc/secure_learning/utils/types.py
tno/mpc/mpyc/secure_learning/utils/util_matrix_vec.py
tno.mpc.mpyc.secure_learning-1.1.1.dist-info/LICENSE
tno.mpc.mpyc.secure_learning-1.1.1.dist-info/METADATA
tno.mpc.mpyc.secure_learning-1.1.1.dist-info/WHEEL
tno.mpc.mpyc.secure_learning-1.1.1.dist-info/namespace_packages.txt
tno.mpc.mpyc.secure_learning-1.1.1.dist-info/top_level.txt
tno.mpc.mpyc.secure_learning-1.1.1.dist-info/RECORD
