Metadata-Version: 2.1
Name: tno.mpc.mpyc.secure-learning
Version: 1.1.1
Summary: Machine learning using Secure Multi-Party Computation
Home-page: https://mpc.tno.nl/
Author: TNO MPC Lab
Author-email: mpclab@tno.nl
Maintainer: TNO MPC Lab
Maintainer-email: mpclab@tno.nl
License: Apache License, Version 2.0
Download-URL: https://pypi.org/project/tno.mpc.mpyc.secure_learning/#files
Project-URL: Documentation, https://docs.mpc.tno.nl/mpyc/secure_learning/1.1.1
Project-URL: Source Code, https://github.com/TNO-MPC/mpyc.secure_learning
Keywords: TNO,MPC,multi-party computation,secure learning,regression,lasso,logistic,SVM,ridge
Platform: any
Classifier: License :: OSI Approved :: Apache Software License
Classifier: Programming Language :: Python :: 3
Classifier: Operating System :: OS Independent
Classifier: Intended Audience :: Developers
Classifier: Intended Audience :: Information Technology
Classifier: Intended Audience :: Science/Research
Classifier: Typing :: Typed
Classifier: Topic :: Security :: Cryptography
Classifier: Topic :: Scientific/Engineering :: Artificial Intelligence
Classifier: Topic :: Scientific/Engineering :: Information Analysis
License-File: LICENSE
Requires-Dist: mpyc
Requires-Dist: numpy
Requires-Dist: tno.mpc.mpyc.exponentiation (>=1.6.0)
Requires-Dist: tno.mpc.mpyc.stubs (>=0.4.2)
Requires-Dist: typing-extensions
Requires-Dist: scikit-learn
Provides-Extra: gmpy
Requires-Dist: gmpy2 (>=2.1.0) ; extra == 'gmpy'
Provides-Extra: tests
Requires-Dist: numpy (>=1.21) ; extra == 'tests'
Requires-Dist: pytest ; extra == 'tests'
Requires-Dist: pytest-asyncio ; extra == 'tests'
